appuidriver/__about__.py
appuidriver/__init__.py
appuidriver/actions.py
appuidriver/cli.py
appuidriver/driver.py
appuidriver/utils.py
appuidriver/common/__init__.py
appuidriver/common/desired_capabilities.py
appuidriver/remote/AppiumHatch.py
appuidriver/remote/AppiumJs.py
appuidriver/remote/AppiumNode.py
appuidriver/remote/__init__.py
appuidriver/remote/appium_wait_until.py
appuidriver/remote/webdriver.py
rtsf_app-1.2.4.dist-info/LICENSE
rtsf_app-1.2.4.dist-info/METADATA
rtsf_app-1.2.4.dist-info/WHEEL
rtsf_app-1.2.4.dist-info/entry_points.txt
rtsf_app-1.2.4.dist-info/top_level.txt
rtsf_app-1.2.4.dist-info/RECORD
