Metadata-Version: 2.1
Name: rtsf-app
Version: 1.2.4
Summary: only for android ui test, base on rtsf
Home-page: https://github.com/RockFeng0/rtsf-app
Author: 罗科峰
Author-email: lkf20031988@163.com
License: MIT
Keywords: test android ui
Platform: UNKNOWN
Requires-Python: >=3.7
Requires-Dist: Appium-Python-Client
Requires-Dist: requests
Requires-Dist: rtsf
Requires-Dist: rtsf-web (>=1.3.6)
Requires-Dist: adbutils
Requires-Dist: selenium (>=4.10.0)
Requires-Dist: beautifulsoup4
